Workbook

Sheet Start Here
B2: Lesson 1.3
B3: Formatting Cells & Number Formats
B4: Beginner · about 100 minutes · Bluestone Health System (fictional)
B6: What you'll learn
B7: • | C7: Apply number formats: Number, Currency vs Accounting, Percentage, Date, Time, Text
B8: • | C8: Write custom number formats (leading zeros, units, colors, thousands)
B9: • | C9: Format fonts, fills, borders, alignment, and wrap text — and avoid merged cells
B10: • | C10: Use Format Painter, cell styles, and themes for consistent reports
B11: • | C11: Understand that formatting changes how a value looks, not the value itself
B13: How to use this workbook
B14: 1. Read the guide | C14: The lesson guide (README) explains each skill with examples: https://github.com/lmansf/learn-excel/tree/main/01-foundations/03-formatting-cells
B15: 2. Practice | C15: Go to the 'Practice' sheet. Type a formula or value into each yellow cell.
B16: 3. Check yourself | C16: The Check column shows ✔ Correct (green) or ✘ Not yet (red).
B17: 4. Bonus | C17: Finished? Try the harder 'Bonus' sheet.
B18: 5. Answers | C18: The 'Answer Key' and 'Bonus Key' sheets are hidden. Right-click any sheet tab → Unhide… → pick one → OK. (Try first!)
B19: Note | C19: Work sheets: Budget (tasks 1–4 and 12–13), Registry (tasks 5–7), Stays (tasks 8–11), and Dec Report (bonus).
B20: Note | C20: Two more hidden sheets, Budget Key and Report Key, show the finished, formatted versions of the Budget and Dec Report sheets. Unhide them to compare once you've tried.
B21: Note | C21: Answers assume US regional settings ($, comma thousands separators, month/day/year dates).
B23: Color legend
B24: Yellow cell | C24: Your answer goes here.
B25: ✔ Correct | C25: Your answer matches the key.
B26: ✘ Not yet | C26: Not matching yet. Check the hint and try again.
B28: Sheets in this workbook
B29: Practice | C29: 13 practice tasks, each with a Check cell.
B30: Bonus | C30: The bonus challenge (5 parts).
B31: About the data | C31: Bluestone Memorial Hospital's 2025 expense budget vs actual by department, two days of ED registrations (12/30–12/31/2025), December 2025 discharges from Cardiac Step-Down, and the Emergency Department's December 2025 budget report (bonus). Every number arrives unformatted, the way it comes out of a source system.
B32: Disclaimer | C32: All people, places, and numbers are synthetic and fictional. Not clinical guidance.

Sheet Practice
A1: Lesson 1.3 · Practice
A2: Tasks 1–4 and 12–13 use the Budget sheet, tasks 5–7 the Registry sheet, and tasks 8–11 the Stays sheet. Work in order, because some tasks build on earlier ones. Most tasks ask you to apply a format and then type exactly what the cell displays, including any dollar sign, commas, parentheses, minus sign, or % sign. Those yellow cells are formatted as Text, so Excel keeps your entry exactly as you type it. Type the answer rather than pasting a copied cell, because pasting brings the cell's number and format along. Tasks 3, 9, and 12 ask for a plain number instead. Answers assume US regional settings.
A3: Type a formula or value in each yellow cell. The Check column turns green when your answer matches. Stuck? Read the hint, then the lesson guide. Answers: right-click a sheet tab → Unhide… → 'Answer Key'.
A4: ="Score: "&COUNTIF(E6:E18,"✔*")&" of 13 auto-checked tasks correct"
A5: # | B5: Task | C5: Hint | D5: Your Answer | E5: Check
A6: 1 | B6: On the Budget sheet, select the Variance cells E5:E21 and press Ctrl + Shift + $ (Mac: ⌃ + Shift + $). What does E11 (Emergency Department, which spent more than its budget) display now? | C6: Negative amounts in this format don't use a minus sign | E6: =IF(IFERROR(D6="",FALSE),"",IF(IFERROR(OR(LOWER(TRIM(D6&""))=LOWER(TRIM('Answer Key'!$C$5&""))),FALSE),"✔ Correct","✘ Not yet"))
A7: 2 | B7: Select the Variance % cells F5:F21, press Ctrl + Shift + % (Mac: ⌃ + Shift + %), then click Home → Increase Decimal once. What does F17 (Orthopedics & Spine) display? | C7: The shortcut shows 0 decimals; each Increase Decimal click adds one | E7: =IF(IFERROR(D7="",FALSE),"",IF(IFERROR(OR(LOWER(TRIM(D7&""))=LOWER(TRIM('Answer Key'!$C$6&""))),FALSE),"✔ Correct","✘ Not yet"))
A8: 3 | B8: C5 already has a finance format: it shows the Laboratory budget in thousands with a K. What number is actually stored in C5? Click the cell and read the formula bar. | C8: The cell shows one thing; the formula bar shows another | E8: =IF(IFERROR(D8="",FALSE),"",IF(IFERROR(AND(ISNUMBER(D8),OR(ABS(D8-'Answer Key'!$C$7)<=0.0001)),FALSE),"✔ Correct","✘ Not yet"))
A9: 4 | B9: Copy C5's format to the rest of the money columns with Format Painter: select C5, double-click Home → Format Painter, drag over C5:E20, then drag over the Total row C21:E21, and press Esc. What does E6 (Pharmacy's variance) display now? | C9: A format with only one section puts a minus sign in front of negatives | E9: =IF(IFERROR(D9="",FALSE),"",IF(IFERROR(OR(LOWER(TRIM(D9&""))=LOWER(TRIM('Answer Key'!$C$8&""))),FALSE),"✔ Correct","✘ Not yet"))
A10: 5 | B10: On the Registry sheet, select the PatientDue cells F5:F24 and click Home → Accounting Number Format (the $ button). Cox, Ronald (row 5) owes nothing for this visit. What character does F5 show where the 0 used to be? | C10: Compare Accounting with Currency in the guide's table | E10: =IF(IFERROR(D10="",FALSE),"",IF(IFERROR(OR(LOWER(TRIM(D10&""))=LOWER(TRIM('Answer Key'!$C$9&"")),LOWER(TRIM(D10&""))="$ -",LOWER(TRIM(D10&""))="$-",LOWER(TRIM(D10&""))="dash",LOWER(TRIM(D10&""))="a dash",LOWER(TRIM(D10&""))="hyphen",LOWER(TRIM(D10&""))="a hyphen",LOWER(TRIM(D10&""))="–",LOWER(TRIM(D10&""))="$ –"),FALSE),"✔ Correct","✘ Not yet"))
A11: 6 | B11: The MRN column lost its leading zeros on the way out of the registration system. Bluestone MRNs are always 8 digits. Select B5:B24, open Format Cells (Ctrl + 1; Mac: ⌘ + 1), choose Custom, and type the code 00000000 in the Type box. What does B13 display? | C11: Each 0 in the code is a digit that always shows, even when it's a zero | E11: =IF(IFERROR(D11="",FALSE),"",IF(IFERROR(OR(LOWER(TRIM(D11&""))=LOWER(TRIM('Answer Key'!$C$10&""))),FALSE),"✔ Correct","✘ Not yet"))
A12: 7 | B12: The Phone column (D) stores 10-digit numbers. Write a custom number format that shows each one the usual US way: the first three digits in parentheses, a space, three digits, a hyphen, and the last four digits. For example, D5 (5555298330) should display as (555) 529-8330. Apply your format to D5:D24, then type the format code you used. | C12: 0 is a digit placeholder; parentheses, spaces, and hyphens can be typed as they are | E12: =IF(IFERROR(D12="",FALSE),"",IF(IFERROR(OR(LOWER(TRIM(SUBSTITUTE(SUBSTITUTE(SUBSTITUTE(D12&"","\",""),CHAR(34),""),"#","0")))="(000) 000-0000",LOWER(TRIM(SUBSTITUTE(SUBSTITUTE(SUBSTITUTE(D12&"","\",""),CHAR(34),""),"#","0")))="[<=9999999]000-0000;(000) 000-0000"),FALSE),"✔ Correct","✘ Not yet"))
A13: 8 | B13: On the Stays sheet, the Admitted column (C) shows serial numbers because the export lost its date format. Select C5:C40 and apply the custom format ddd mm/dd/yyyy h:mm AM/PM. What does C6 display? | C13: ddd is the short day name; mm right after h means minutes | E13: =IF(IFERROR(D13="",FALSE),"",IF(IFERROR(OR(LOWER(TRIM(D13&""))=LOWER(TRIM('Answer Key'!$C$12&""))),FALSE),"✔ Correct","✘ Not yet"))
A14: 9 | B14: The LOS (days) column is formatted to show one decimal place. E7 shows 3.1. What value is actually stored in that cell? Read the formula bar and enter at least 4 decimal places. | C14: Formatting rounds the display, not the value | E14: =IF(IFERROR(D14="",FALSE),"",IF(IFERROR(AND(ISNUMBER(D14),OR(ABS(D14-'Answer Key'!$C$13)<=0.0001)),FALSE),"✔ Correct","✘ Not yet"))
A15: 10 | B15: Hospitals often track length of stay in hours. Select E5:E40 and apply the custom format [h]:mm. What does E15 (the longest stay of the month) display? | C15: Square brackets let the hours keep counting past 24 | E15: =IF(IFERROR(D15="",FALSE),"",IF(IFERROR(OR(LOWER(TRIM(D15&""))=LOWER(TRIM('Answer Key'!$C$14&""))),FALSE),"✔ Correct","✘ Not yet"))
A16: 11 | B16: Column G (LOS vs Expected) stores LOS minus the diagnosis's expected LOS, in days, so a positive value means the patient stayed longer than expected. Write a two-section custom format for G5:G40: positive values in red with a plus sign and the word days (like +2.1 days), and negative values with a minus sign (like -0.4 days), each with one decimal. What does G5 display? | C16: Sections are separated by semicolons: positive;negative. The second section needs its own minus sign | E16: =IF(IFERROR(D16="",FALSE),"",IF(IFERROR(OR(LOWER(TRIM(D16&""))=LOWER(TRIM('Answer Key'!$C$15&""))),FALSE),"✔ Correct","✘ Not yet"))
A17: 12 | B17: Back on the Budget sheet, column A labels each department's service line with merged cells. Select A5:A20 and read Count on the status bar (it counts cells that aren't empty). How many of those 16 cells actually contain a service-line label? | C17: A merged block stores its text in one cell only | E17: =IF(IFERROR(D17="",FALSE),"",IF(IFERROR(AND(ISNUMBER(D17),OR(ABS(D17-'Answer Key'!$C$16)<=0.0001)),FALSE),"✔ Correct","✘ Not yet"))
A18: 13 | B18: Finish the Budget report so it looks like the hidden Budget Key sheet: (1) unmerge A1:F1 and center the title with Center Across Selection; (2) unmerge column A and fill each service line down so every row has its label; (3) make header row 4 bold with white text on a dark blue fill, wrapped and centered; (4) add All Borders to A4:F21; (5) apply the Total cell style to A21:F21; (6) select A4:F21 and AutoFit the columns with Home → Format → AutoFit Column Width. Then zoom in on row 21: what kind of line does the Total style draw along the bottom of the row? Answer in a word or two. | C18: Cell Styles is on the Home tab; look closely at the bottom edge of the total row | E18: =IF(IFERROR(D18="",FALSE),"",IF(IFERROR(OR(LOWER(TRIM(D18&""))=LOWER(TRIM('Answer Key'!$C$17&"")),LOWER(TRIM(D18&""))="double line",LOWER(TRIM(D18&""))="a double line",LOWER(TRIM(D18&""))="double border",LOWER(TRIM(D18&""))="a double border",LOWER(TRIM(D18&""))="double bottom border",LOWER(TRIM(D18&""))="a double bottom border",LOWER(TRIM(D18&""))="bottom double border",LOWER(TRIM(D18&""))="double line border",LOWER(TRIM(D18&""))="double underline",LOWER(TRIM(D18&""))="double-line",LOWER(TRIM(D18&""))="two lines",LOWER(TRIM(D18&""))="2 lines",LOWER(TRIM(D18&""))="double lines"),FALSE),"✔ Correct","✘ Not yet"))

Sheet Budget
A1: Bluestone Memorial Hospital · 2025 Expense Budget vs Actual
A2: Finance system export, 12/31/2025. Variance = Budget − Actual (negative = over budget). Variance % = Variance ÷ Budget.
A4: Service Line | B4: Department | C4: Budget | D4: Actual | E4: Variance | F4: Variance %
A5: Ancillary | B5: Laboratory | C5: 11736897 | D5: 11940898 | E5: -204001 | F5: -0.01738117
B6: Pharmacy | C6: 6946916 | D6: 7177608 | E6: -230692 | F6: -0.033207829
B7: Radiology | C7: 9165952 | D7: 8908151 | E7: 257801 | F7: 0.028125938
A8: Behavioral Health | B8: Behavioral Health | C8: 6261550 | D8: 6272799 | E8: -11249 | F8: -0.00179652
A9: Cardiovascular | B9: Cardiac Step-Down | C9: 8348725 | D9: 8557688 | E9: -208963 | F9: -0.025029331
A10: Critical Care | B10: Intensive Care Unit | C10: 11314622 | D10: 11343688 | E10: -29066 | F10: -0.0025688883
A11: Emergency | B11: Emergency Department | C11: 16990557 | D11: 17563319 | E11: -572762 | F11: -0.033710608
A12: Medicine | B12: Medical-Surgical 4 West | C12: 12523079 | D12: 12172461 | E12: 350618 | F12: 0.027997747
B13: Medical-Surgical 5 East | C13: 11131624 | D13: 11370076 | E13: -238452 | F13: -0.021421133
B14: Observation Unit | C14: 4174351 | D14: 4147444 | E14: 26907 | F14: 0.0064457924
A15: Neuroscience | B15: Neuroscience & Stroke | C15: 5565810 | D15: 5586800 | E15: -20990 | F15: -0.003771239
A16: Oncology | B16: Oncology | C16: 8143173 | D16: 8259303 | E16: -116130 | F16: -0.014261026
A17: Orthopedics | B17: Orthopedics & Spine | C17: 7652992 | D17: 8006587 | E17: -353595 | F17: -0.046203498
A18: Surgery | B18: Perioperative Services | C18: 18294658 | D18: 18584793 | E18: -290135 | F18: -0.015859001
A19: Women & Children | B19: Labor & Delivery | C19: 6957277 | D19: 7118781 | E19: -161504 | F19: -0.02321368
B20: Pediatrics | C20: 4870099 | D20: 4851882 | E20: 18217 | F20: 0.003740581
A21: Total | C21: 150078282 | D21: 151862278 | E21: -1783996 | F21: -0.011887103

Sheet Registry
A1: Bluestone Memorial ED · registrations, 12/30–12/31/2025 (export)
A2: MRN and Phone arrived as plain numbers, so the leading zeros and punctuation are gone. PatientDue = the patient's share of this visit's claim, in dollars.
A4: Arrived | B4: MRN | C4: Patient | D4: Phone | E4: Payer | F4: PatientDue
A5: 46021.046 | B5: 3601518 | C5: Cox, Ronald | D5: 5555298330 | E5: State Medicaid | F5: 0
A6: 46021.344 | B6: 1927734 | C6: Yilmaz, Natalie | D6: 5559671131 | E6: Evergreen Mutual Insurance | F6: 212.08
A7: 46021.379 | B7: 6086499 | C7: Nguyen, Liam | D7: 5556619507 | E7: Self-Pay | F7: 385.94
A8: 46021.415 | B8: 5077908 | C8: Garza, Rosa | D8: 5555169517 | E8: Keystone Health Partners | F8: 801.3
A9: 46021.477 | B9: 5094809 | C9: Gomez, Elizabeth | D9: 5557012318 | E9: State Medicaid | F9: 0
A10: 46021.493 | B10: 6814000 | C10: Collins, Nicole | D10: 5554961382 | E10: State Medicaid | F10: 0
A11: 46021.678 | B11: 2001795 | C11: Lane, Frances | D11: 5558013246 | E11: State Medicaid | F11: 0
A12: 46021.886 | B12: 1518534 | C12: Hernandez, Albert | D12: 5555060873 | E12: Medicare | F12: 138.68
A13: 46022.302 | B13: 440415 | C13: Hunter, Edward | D13: 5556842598 | E13: State Medicaid | F13: 0
A14: 46022.402 | B14: 3279315 | C14: Vazquez, Harper | D14: 5553472385 | E14: Medicare | F14: 0
A15: 46022.46 | B15: 9254099 | C15: Stone, Ethan | D15: 5556723317 | E15: Evergreen Mutual Insurance | F15: 84.13
A16: 46022.487 | B16: 2718484 | C16: King, Gerald | D16: 5556085815 | E16: State Medicaid | F16: 0
... A24: 46022.747 | B24: 1508745 | C24: Harrison, Catherine | D24: 5553154437 | E24: State Medicaid | F24: 0

Sheet Stays
A1: Cardiac Step-Down (Bluestone Memorial) · inpatient discharges · December 2025
A2: Admitted lost its date format in the export. LOS = Discharged − Admitted, in days. Expected LOS is the diagnosis benchmark. LOS vs Expected = LOS − Expected LOS (positive = stayed longer than expected).
A4: EncounterID | B4: Diagnosis | C4: Admitted | D4: Discharged | E4: LOS (days) | F4: Expected LOS | G4: LOS vs Expected
A5: ENC120695 | B5: Heart failure, unspecified | C5: 45990.536 | D5: 45992.661 | E5: 2.125 | F5: 4.1 | G5: -1.975
A6: ENC120564 | B6: Heart failure, unspecified | C6: 45986.499 | D6: 45992.689 | E6: 6.1902778 | F6: 4.1 | G6: 2.0903
A7: ENC120742 | B7: Unspecified atrial fibrillation | C7: 45992.392 | D7: 45995.533 | E7: 3.1409722 | F7: 2.9 | G7: 0.241
A8: ENC120707 | B8: Unspecified atrial fibrillation | C8: 45990.812 | D8: 45995.636 | E8: 4.8243056 | F8: 2.9 | G8: 1.9243
A9: ENC120879 | B9: Non-ST elevation (NSTEMI) myocardial infarction | C9: 45995.484 | D9: 45996.54 | E9: 1.0555556 | F9: 3.4 | G9: -2.3444
A10: ENC120694 | B10: Heart failure, unspecified | C10: 45990.534 | D10: 45996.724 | E10: 6.1902778 | F10: 4.1 | G10: 2.0903
A11: ENC120833 | B11: Non-ST elevation (NSTEMI) myocardial infarction | C11: 45994.422 | D11: 45997.511 | E11: 3.0888889 | F11: 3.4 | G11: -0.3111
A12: ENC120883 | B12: Unspecified atrial fibrillation | C12: 45995.712 | D12: 45998.616 | E12: 2.9041667 | F12: 2.9 | G12: 0.0042
A13: ENC120956 | B13: Heart failure, unspecified | C13: 45997.021 | D13: 45999.672 | E13: 2.6506944 | F13: 4.1 | G13: -1.4493
A14: ENC120906 | B14: Heart failure, unspecified | C14: 45995.987 | D14: 46000.642 | E14: 4.6555556 | F14: 4.1 | G14: 0.5556
A15: ENC120589 | B15: Heart failure, unspecified | C15: 45987.164 | D15: 46004.363 | E15: 17.199306 | F15: 4.1 | G15: 13.0993
A16: ENC121171 | B16: Heart failure, unspecified | C16: 46002.822 | D16: 46005.654 | E16: 2.8326389 | F16: 4.1 | G16: -1.2674
... A40: ENC121789 | B40: Unspecified atrial fibrillation | C40: 46020.962 | D40: 46022.633 | E40: 1.6708333 | F40: 2.9 | G40: -1.2292

Sheet Bonus
A1: Lesson 1.3 · Bonus: Format the ED's monthly budget report
A2: The Emergency Department director presents the December 2025 operating report to the CFO next week. Finance's style guide has five rules for department reports. Apply them on the Dec Report sheet, writing every custom format code yourself. Then type what each listed Dec Report cell displays into the yellow cells on the Bonus sheet. When you finish, compare your sheet with the hidden Report Key sheet. - Rule 1: Center the title across A1:I1 without merging. Make the header row bold white text on a dark blue fill, wrapped and centered. Give the Total row the Total cell style. - Rule 2: Show Dec Budget and Dec Actual in thousands with one decimal place, a dollar sign, and a K, so 843,879 displays as $843.9K. - Rule 3: Show both Variance columns the same way, except that negative variances (over budget) are red and in parentheses instead of having a minus sign, so -25,403 displays as ($25.4K). - Rule 4: Show both Var % columns with one decimal place, with negatives red and in parentheses, so -0.1075… displays as (10.8%). - Rule 5: Show YTD Budget and YTD Actual with a dollar sign: in millions with two decimals and an M when the amount is 1,000,000 or more (10,290,782 displays as $10.29M), and otherwise in thousands with no decimals and a K.
A3: Type a formula or value in each yellow cell. The Check column turns green when your answer matches. Stuck? Read the hint, then the lesson guide. Answers: right-click a sheet tab → Unhide… → 'Bonus Key'.
A4: ="Score: "&COUNTIF(E6:E10,"✔*")&" of 5 auto-checked tasks correct"
A5: # | B5: Task | C5: Hint | D5: Your Answer | E5: Check
A6: B1 | B6: Rule 2: on the Dec Report sheet, what does C5 (Employee Benefits, Dec Actual) display? | C6: One comma after the last digit placeholder divides the display by 1,000 | E6: =IF(IFERROR(D6="",FALSE),"",IF(IFERROR(OR(LOWER(TRIM(D6&""))=LOWER(TRIM('Bonus Key'!$C$5&""))),FALSE),"✔ Correct","✘ Not yet"))
A7: B2 | B7: Rule 3: on the Dec Report sheet, what does D11 (Salaries & Wages, Dec Variance) display? | C7: Two sections: positive;negative. Put the color first in the negative section | E7: =IF(IFERROR(D7="",FALSE),"",IF(IFERROR(OR(LOWER(TRIM(D7&""))=LOWER(TRIM('Bonus Key'!$C$6&""))),FALSE),"✔ Correct","✘ Not yet"))
A8: B3 | B8: Rule 4: on the Dec Report sheet, what does I6 (Equipment & Maintenance, YTD Var %) display? | C8: A % in a custom code multiplies by 100, in every section where it appears | E8: =IF(IFERROR(D8="",FALSE),"",IF(IFERROR(OR(LOWER(TRIM(D8&""))=LOWER(TRIM('Bonus Key'!$C$7&""))),FALSE),"✔ Correct","✘ Not yet"))
A9: B4 | B9: Rule 5: on the Dec Report sheet, what does G12 (the Total row's YTD Actual) display? | C9: Conditions go in square brackets at the start of a section, like [>=1000000] | E9: =IF(IFERROR(D9="",FALSE),"",IF(IFERROR(OR(LOWER(TRIM(D9&""))=LOWER(TRIM('Bonus Key'!$C$8&""))),FALSE),"✔ Correct","✘ Not yet"))
A10: B5 | B10: Rule 5: on the Dec Report sheet, what does F8 (Other Operating, YTD Budget) display? | C10: A value that fails the first condition moves on to the next section | E10: =IF(IFERROR(D10="",FALSE),"",IF(IFERROR(OR(LOWER(TRIM(D10&""))=LOWER(TRIM('Bonus Key'!$C$9&""))),FALSE),"✔ Correct","✘ Not yet"))

Sheet Dec Report
A1: Emergency Department · Monthly Operating Expense Report · December 2025
A2: Bluestone Memorial Hospital, cost center 6100. Variance = Budget − Actual (negative = over budget). YTD = January–December 2025.
A4: Expense category | B4: Dec Budget | C4: Dec Actual | D4: Dec Variance | E4: Dec Var % | F4: YTD Budget | G4: YTD Actual | H4: YTD Variance | I4: YTD Var %
A5: Employee Benefits | B5: 236286 | C5: 261689 | D5: -25403 | E5: -0.10750954 | F5: 2782078 | G5: 2857681 | H5: -75603 | I5: -0.027175011
A6: Equipment & Maintenance | B6: 42194 | C6: 48423 | D6: -6229 | E6: -0.14762762 | F6: 496801 | G6: 537673 | H6: -40872 | I6: -0.082270366
A7: Medical Supplies | B7: 118143 | C7: 114612 | D7: 3531 | E7: 0.029887509 | F7: 1391039 | G7: 1381877 | H7: 9162 | I7: 0.0065864437
A8: Other Operating | B8: 25316 | C8: 25147 | D8: 169 | E8: 0.0066756202 | F8: 298078 | G8: 312576 | H8: -14498 | I8: -0.048638276
A9: Pharmaceuticals | B9: 75949 | C9: 71566 | D9: 4383 | E9: 0.057709779 | F9: 894238 | G9: 923543 | H9: -29305 | I9: -0.032770918
A10: Purchased Services | B10: 101266 | C10: 117116 | D10: -15850 | E10: -0.15651848 | F10: 1192324 | G10: 1259187 | H10: -66863 | I10: -0.056077878
A11: Salaries & Wages | B11: 843879 | C11: 891650 | D11: -47771 | E11: -0.056608827 | F11: 9935999 | G11: 10290782 | H11: -354783 | I11: -0.035706827
A12: Total | B12: 1443033 | C12: 1530203 | D12: -87170 | E12: -0.060407489 | F12: 16990557 | G12: 17563319 | H12: -572762 | I12: -0.033710608

Sheet Answer Key
A1: 🔑 Answer Key — Lesson 1.3
A2: Spoiler alert: try every task before reading this sheet. Column C is the value the Check column compares against. Column D is a sample solution, and column E recalculates a formula for it live, proving the answer.
A4: # | B4: Task | C4: Answer | D4: Sample solution | E4: Live result | F4: Explanation
A5: 1 | B5: On the Budget sheet, select the Variance cells E5:E21 and press Ctrl + Shift + $ (Mac: ⌃ + Shift + $). What does E11 (Emergency Department, which spent more than its budget) display now? | C5: ($572,762.00) | D5: 1. Select Budget!E5:E21. 2. Press Ctrl + Shift + $ (Mac: ⌃ + Shift + $). 3. Read E11. | E5: {=TEXT(Budget!E11,"$#,##0.00_);($#,##0.00)")} | F5: The shortcut applies the Currency format with two decimals, whose code is $#,##0.00_);($#,##0.00). The part after the semicolon is used for negative numbers, and it wraps them in parentheses instead of showing a minus sign, the way accountants write losses. The stored value is still -572762. Click the cell and look at the formula bar to confirm. (The key's live formula uses TEXT, a Lesson 2.2 function that returns what a format would display.)
A6: 2 | B6: Select the Variance % cells F5:F21, press Ctrl + Shift + % (Mac: ⌃ + Shift + %), then click Home → Increase Decimal once. What does F17 (Orthopedics & Spine) display? | C6: -4.6% | D6: 1. Select Budget!F5:F21. 2. Press Ctrl + Shift + % (Mac: ⌃ + Shift + %). The cells show whole percentages. 3. Click Home → Increase Decimal (the .00 button with the left arrow) once. 4. Read F17. | E6: {=TEXT(Budget!F17,"0.0%")} | F6: The cell stores -0.046203… The Percentage format multiplies by 100 for display only and adds the % sign, so it shows -5% at first and -4.6% after one Increase Decimal click. Excel rounds the display, but the stored value keeps every digit.
A7: 3 | B7: C5 already has a finance format: it shows the Laboratory budget in thousands with a K. What number is actually stored in C5? Click the cell and read the formula bar. | C7: 11736897 | D7: Click Budget!C5 and read the formula bar. It shows the full dollar amount. | E7: {=Budget!C5} | F7: The cell displays $11,737K, but it stores 11,736,897. The custom code $#,##0,"K" ends with a comma after the last 0, which tells Excel to display the number divided by 1,000. Any formula that uses C5 still gets the full amount, so totals stay exact even when every cell is shown in thousands.
A8: 4 | B8: Copy C5's format to the rest of the money columns with Format Painter: select C5, double-click Home → Format Painter, drag over C5:E20, then drag over the Total row C21:E21, and press Esc. What does E6 (Pharmacy's variance) display now? | C8: -$231K | D8: 1. Select Budget!C5. 2. Double-click Home → Format Painter (the paintbrush). Double-clicking keeps it switched on. 3. Drag over C5:E20, then drag over the Total row, C21:E21. 4. Press Esc (or click the paintbrush again) to switch it off. 5. Read E6. | E8: {=TEXT(Budget!E6,"$#,##0,""K""")} | F8: Format Painter copies all of C5's formatting (number format, font, fill, borders, alignment) onto the cells you paint. $#,##0,"K" has a single section, so Excel uses it for every number and simply puts a minus sign in front of negatives: -230,692 shows as -$231K. The parentheses from task 1 are gone because each cell has only one number format, and the newest one wins. A single click on Format Painter paints once. A double-click lets you paint several ranges until you press Esc.
A9: 5 | B9: On the Registry sheet, select the PatientDue cells F5:F24 and click Home → Accounting Number Format (the $ button). Cox, Ronald (row 5) owes nothing for this visit. What character does F5 show where the 0 used to be? | C9: - | D9: 1. Select Registry!F5:F24. 2. Click the $ button in the Number group of the Home tab (its ScreenTip says Accounting Number Format). 3. Look at F5: the $ sits at the left edge and a dash sits near the right. | E9: — | F9: The Accounting code is _($* #,##0.00_);_($* (#,##0.00);_($* "-"??_);_(@_). Its third section (zero) prints a dash, so a column of balances shows which patients owe nothing at a glance. Accounting also pins the $ to the left edge of the cell and lines up the decimal points, and it always shows negatives in parentheses. Currency puts the $ right next to the number and shows $0.00 for zero. The cell still stores 0.
A10: 6 | B10: The MRN column lost its leading zeros on the way out of the registration system. Bluestone MRNs are always 8 digits. Select B5:B24, open Format Cells (Ctrl + 1; Mac: ⌘ + 1), choose Custom, and type the code 00000000 in the Type box. What does B13 display? | C10: 00440415 | D10: 1. Select Registry!B5:B24 and press Ctrl + 1 (Mac: ⌘ + 1). 2. On the Number tab choose Custom, replace the Type box with 00000000, and click OK. 3. Read B13. | E10: {=TEXT(Registry!B13,"00000000")} | F10: The cell stores the number 440415. Each 0 in 00000000 is a placeholder that forces a digit, so Excel pads the display to 8 digits: 00440415. This fixes how the MRN looks on a printed list. The value is still a number, though, so it won't match the text MRN 00440415 in another system or in a lookup. When you control data entry, store IDs as text instead (Lesson 1.2).
A11: 7 | B11: The Phone column (D) stores 10-digit numbers. Write a custom number format that shows each one the usual US way: the first three digits in parentheses, a space, three digits, a hyphen, and the last four digits. For example, D5 (5555298330) should display as (555) 529-8330. Apply your format to D5:D24, then type the format code you used. | C11: (000) 000-0000 | D11: 1. Select Registry!D5:D24 and press Ctrl + 1 (Mac: ⌘ + 1). 2. Choose Custom and type (000) 000-0000 in the Type box. Click OK. 3. Type (000) 000-0000 in the answer cell. | E11: — | F11: (000) 000-0000 has ten 0 placeholders, filled from the right with the number's ten digits. Parentheses, the space, and the hyphen are characters Excel prints as-is, without quotes. The check also accepts (###) ###-#### (the same for 10-digit numbers) and Excel's built-in Special → Phone Number format, [<=9999999]###-####;(###) ###-####, which you'll see in the Custom box if you used Special.
A12: 8 | B12: On the Stays sheet, the Admitted column (C) shows serial numbers because the export lost its date format. Select C5:C40 and apply the custom format ddd mm/dd/yyyy h:mm AM/PM. What does C6 display? | C12: Tue 11/25/2025 11:58 AM | D12: 1. Select Stays!C5:C40 and press Ctrl + 1 (Mac: ⌘ + 1). 2. Choose Custom, type ddd mm/dd/yyyy h:mm AM/PM, and click OK. 3. Read C6. | E12: {=TEXT(Stays!C6,"ddd mm/dd/yyyy h:mm AM/PM")} | F12: The cell stores 45986.49861: the whole number is the date and the decimal is the time of day. ddd gives the short day name, mm/dd/yyyy the date with leading zeros, and h:mm AM/PM a 12-hour time without a leading zero. Because mm follows h, Excel reads it as minutes, not months.
A13: 9 | B13: The LOS (days) column is formatted to show one decimal place. E7 shows 3.1. What value is actually stored in that cell? Read the formula bar and enter at least 4 decimal places. | C13: 3.1409722 | D13: Click Stays!E7 and read the formula bar. | E13: {=Stays!E7} | F13: The stay lasted 4,523 minutes, and 4,523 ÷ 1,440 minutes per day = 3.14097222… days. The 0.0 format only rounds what you see. If you add up the LOS column, Excel adds the full values, so a total can differ slightly from the sum of the rounded numbers on screen. Use ROUND (Lesson 1.4) when the rounded number is the one you mean.
A14: 10 | B14: Hospitals often track length of stay in hours. Select E5:E40 and apply the custom format [h]:mm. What does E15 (the longest stay of the month) display? | C14: 412:47 | D14: 1. Select Stays!E5:E40 and press Ctrl + 1 (Mac: ⌘ + 1). 2. Choose Custom, type [h]:mm, and click OK. 3. Read E15. | E14: {=TEXT(Stays!E15,"[h]:mm")} | F14: The cell stores 17.1993 days. One day is 24 hours, so that's 412 hours and 47 minutes. [h] shows elapsed hours. Plain h:mm would show 4:47, the clock time, because ordinary hours roll back to 0 every 24 hours. Use [h]:mm for any duration that can pass a day: LOS, shift hours, ED boarding time.
A15: 11 | B15: Column G (LOS vs Expected) stores LOS minus the diagnosis's expected LOS, in days, so a positive value means the patient stayed longer than expected. Write a two-section custom format for G5:G40: positive values in red with a plus sign and the word days (like +2.1 days), and negative values with a minus sign (like -0.4 days), each with one decimal. What does G5 display? | C15: -2.0 days | D15: 1. Select Stays!G5:G40 and press Ctrl + 1 (Mac: ⌘ + 1). 2. Choose Custom, type [Red]+0.0 "days";-0.0 "days", and click OK. 3. Read G5. | E15: {=TEXT(Stays!G5,"[Red]+0.0 ""days"";-0.0 ""days""")} | F15: [Red]+0.0 "days";-0.0 "days" has two sections. The first (positive and zero) starts with the color [Red], then a literal +, the number, and the text "days" in quotes. The second section (negative) has no color. When a format has a negative section, Excel stops adding the minus sign for you, so you type it yourself. Without it, -1.975 would display as 2.0 days and look like a positive number. 15 of the 36 stays show in red because they lasted longer than expected.
A16: 12 | B16: Back on the Budget sheet, column A labels each department's service line with merged cells. Select A5:A20 and read Count on the status bar (it counts cells that aren't empty). How many of those 16 cells actually contain a service-line label? | C16: 11 | D16: Select Budget!A5:A20 and read Count on the status bar. | E16: {=COUNTA(Budget!A5:A20)} | F16: There are 16 departments but only 11 labels, because a merged block keeps its value in the top-left cell and the other cells are empty. For example, only the first Medicine row really says Medicine. Sort, filter, copy, or count by service line and the rows under each block behave as if they had no service line. Excel even refuses to sort a range whose merged cells are different sizes. Task 13 replaces the merges with a label on every row. (After task 13, the key's live COUNTA shows 16, because every row then has its label.)
A17: 13 | B17: Finish the Budget report so it looks like the hidden Budget Key sheet: (1) unmerge A1:F1 and center the title with Center Across Selection; (2) unmerge column A and fill each service line down so every row has its label; (3) make header row 4 bold with white text on a dark blue fill, wrapped and centered; (4) add All Borders to A4:F21; (5) apply the Total cell style to A21:F21; (6) select A4:F21 and AutoFit the columns with Home → Format → AutoFit Column Width. Then zoom in on row 21: what kind of line does the Total style draw along the bottom of the row? Answer in a word or two. | C17: double | D17: 1. Title: select A1 and click Home → Merge & Center to unmerge it. Select A1:F1, press Ctrl + 1 (Mac: ⌘ + 1), and on the Alignment tab set Horizontal to Center Across Selection. 2. Service lines: select A5:A20 and choose Home → Merge & Center ▾ → Unmerge Cells. Then, for each block that now has blank cells under its label (A5:A7, A12:A14, A19:A20), select the block and press Ctrl + D (Mac: ⌘ + D) to fill the label down. 3. Header: select A4:F4. Press Ctrl + B (Mac: ⌘ + B), pick Home → Font Color ▾ → White, Home → Fill Color ▾ → Dark Blue (or any dark theme color), then click Wrap Text and Center. 4. Borders: select A4:F21 and choose Home → Borders ▾ → All Borders. 5. Total row: select A21:F21 and choose Home → Cell Styles → Total (in the Titles and Headings group). 6. AutoFit: select A4:F21 (just the table, not whole columns) and choose Home → Format → AutoFit Column Width (Windows KeyTips Alt, H, O, I). Selecting whole columns would also measure the long note in A2, and column A would grow as wide as that sentence. 7. Unhide Budget Key (right-click a sheet tab → Unhide…) and compare. | E17: — | F17: The built-in Total style makes the text bold and draws a thin line above the row and a double line below it, the accounting convention for a grand total. Because it's a style, every total row you apply it to looks the same. Its lines use a theme color, so if you switched the workbook to another theme in Page Layout → Themes, the Total lines would change color while a header fill picked from Standard Colors (Dark Blue) would stay put. Center Across Selection looks exactly like Merge & Center but leaves every cell independent, so sorting, selecting columns, and copying keep working.

Sheet Bonus Key
A1: 🔑 Bonus Key — Lesson 1.3
A2: Spoiler alert: try every task before reading this sheet. Column C is the value the Check column compares against. Column D is a sample solution, and column E recalculates a formula for it live, proving the answer.
A4: # | B4: Task | C4: Answer | D4: Sample solution | E4: Live result | F4: Explanation
A5: B1 | B5: Rule 2: on the Dec Report sheet, what does C5 (Employee Benefits, Dec Actual) display? | C5: $261.7K | D5: 1. Rule 1 uses the same steps as practice task 13: select 'Dec Report'!A1:I1 and set Center Across Selection (Ctrl + 1, Mac: ⌘ + 1 → Alignment tab), style the header A4:I4 (bold, white font, dark blue fill, Wrap Text, Center), and apply Home → Cell Styles → Total to A12:I12. 2. Rule 2: select 'Dec Report'!B5:C12, press Ctrl + 1 (Mac: ⌘ + 1), choose Custom, and type $#,##0.0,"K". 3. Read C5. | E5: {=TEXT('Dec Report'!C5,"$#,##0.0,""K""")} | F5: 261,689 ÷ 1,000 = 261.689, shown with one decimal as $261.7K. The comma between # and ##0 is the thousands separator. The comma after 0.0 is the scaling comma.
A6: B2 | B6: Rule 3: on the Dec Report sheet, what does D11 (Salaries & Wages, Dec Variance) display? | C6: ($47.8K) | D6: Select 'Dec Report'!D5:D12, then hold Ctrl (Mac: ⌘) and drag over H5:H12 to add the YTD Variance column. Apply the custom format $#,##0.0,"K";Red. | E6: {=TEXT('Dec Report'!D11,"$#,##0.0,""K"";[Red]($#,##0.0,""K"")")} | F6: The first section formats positive variances (under budget). The second section starts with [Red] and wraps the same thousands pattern in parentheses, so -47,771 shows as ($47.8K) in red. Because the format has a negative section, Excel adds no minus sign. In December, 5 of the 8 Dec Variance cells (including the total) turn red.
A7: B3 | B7: Rule 4: on the Dec Report sheet, what does I6 (Equipment & Maintenance, YTD Var %) display? | C7: (8.2%) | D7: Select 'Dec Report'!E5:E12, then hold Ctrl (Mac: ⌘) and drag over I5:I12. Apply the custom format 0.0%;Red. | E7: {=TEXT('Dec Report'!I6,"0.0%;[Red](0.0%)")} | F7: The cell stores -0.082270… Each section has its own %, so both multiply by 100. The negative section adds [Red] and parentheses: (8.2%).
A8: B4 | B8: Rule 5: on the Dec Report sheet, what does G12 (the Total row's YTD Actual) display? | C8: $17.56M | D8: Select 'Dec Report'!F5:G12 and apply the custom format [>=1000000]$#,##0.00,,"M";[>=1000]$#,##0,"K";$#,##0. | E8: {=TEXT('Dec Report'!G12,"[>=1000000]$#,##0.00,,""M"";[>=1000]$#,##0,""K"";$#,##0")} | F8: A condition in square brackets replaces the usual positive/negative meaning of a section. [>=1000000] sends 17,563,319 to the first section, where two scaling commas divide by 1,000,000: $17.56M. This total matches the Emergency Department's 2025 actual on the Budget sheet, because December closes the fiscal year.
A9: B5 | B9: Rule 5: on the Dec Report sheet, what does F8 (Other Operating, YTD Budget) display? | C9: $298K | D9: Same format as the previous part. Check that values under 1,000,000 fall through to the K section. | E9: {=TEXT('Dec Report'!F8,"[>=1000000]$#,##0.00,,""M"";[>=1000]$#,##0,""K"";$#,##0")} | F9: 298,078 is less than 1,000,000, so Excel skips the first section and uses [>=1000]$#,##0,"K": $298K. The full code is [>=1000000]$#,##0.00,,"M";[>=1000]$#,##0,"K";$#,##0. Its third section catches anything under 1,000. Without conditions, every value would get the same scale, and a $298K line would show as $0.30M.

Sheet Budget Key
A1: Bluestone Memorial Hospital · 2025 Expense Budget vs Actual
A2: Finance system export, 12/31/2025. Variance = Budget − Actual (negative = over budget). Variance % = Variance ÷ Budget. · Finished version for task 13: compare with your Budget sheet.
A4: Service Line | B4: Department | C4: Budget | D4: Actual | E4: Variance | F4: Variance %
A5: Ancillary | B5: Laboratory | C5: 11736897 | D5: 11940898 | E5: -204001 | F5: -0.01738117
A6: Ancillary | B6: Pharmacy | C6: 6946916 | D6: 7177608 | E6: -230692 | F6: -0.033207829
A7: Ancillary | B7: Radiology | C7: 9165952 | D7: 8908151 | E7: 257801 | F7: 0.028125938
A8: Behavioral Health | B8: Behavioral Health | C8: 6261550 | D8: 6272799 | E8: -11249 | F8: -0.00179652
A9: Cardiovascular | B9: Cardiac Step-Down | C9: 8348725 | D9: 8557688 | E9: -208963 | F9: -0.025029331
A10: Critical Care | B10: Intensive Care Unit | C10: 11314622 | D10: 11343688 | E10: -29066 | F10: -0.0025688883
A11: Emergency | B11: Emergency Department | C11: 16990557 | D11: 17563319 | E11: -572762 | F11: -0.033710608
A12: Medicine | B12: Medical-Surgical 4 West | C12: 12523079 | D12: 12172461 | E12: 350618 | F12: 0.027997747
A13: Medicine | B13: Medical-Surgical 5 East | C13: 11131624 | D13: 11370076 | E13: -238452 | F13: -0.021421133
A14: Medicine | B14: Observation Unit | C14: 4174351 | D14: 4147444 | E14: 26907 | F14: 0.0064457924
A15: Neuroscience | B15: Neuroscience & Stroke | C15: 5565810 | D15: 5586800 | E15: -20990 | F15: -0.003771239
A16: Oncology | B16: Oncology | C16: 8143173 | D16: 8259303 | E16: -116130 | F16: -0.014261026
... A20: Women & Children | B20: Pediatrics | C20: 4870099 | D20: 4851882 | E20: 18217 | F20: 0.003740581
A21: Total | C21: 150078282 | D21: 151862278 | E21: -1783996 | F21: -0.011887103

Sheet Report Key
A1: Emergency Department · Monthly Operating Expense Report · December 2025
A2: Bluestone Memorial Hospital, cost center 6100. Variance = Budget − Actual (negative = over budget). YTD = January–December 2025.
A4: Expense category | B4: Dec Budget | C4: Dec Actual | D4: Dec Variance | E4: Dec Var % | F4: YTD Budget | G4: YTD Actual | H4: YTD Variance | I4: YTD Var %
A5: Employee Benefits | B5: 236286 | C5: 261689 | D5: -25403 | E5: -0.10750954 | F5: 2782078 | G5: 2857681 | H5: -75603 | I5: -0.027175011
A6: Equipment & Maintenance | B6: 42194 | C6: 48423 | D6: -6229 | E6: -0.14762762 | F6: 496801 | G6: 537673 | H6: -40872 | I6: -0.082270366
A7: Medical Supplies | B7: 118143 | C7: 114612 | D7: 3531 | E7: 0.029887509 | F7: 1391039 | G7: 1381877 | H7: 9162 | I7: 0.0065864437
A8: Other Operating | B8: 25316 | C8: 25147 | D8: 169 | E8: 0.0066756202 | F8: 298078 | G8: 312576 | H8: -14498 | I8: -0.048638276
A9: Pharmaceuticals | B9: 75949 | C9: 71566 | D9: 4383 | E9: 0.057709779 | F9: 894238 | G9: 923543 | H9: -29305 | I9: -0.032770918
A10: Purchased Services | B10: 101266 | C10: 117116 | D10: -15850 | E10: -0.15651848 | F10: 1192324 | G10: 1259187 | H10: -66863 | I10: -0.056077878
A11: Salaries & Wages | B11: 843879 | C11: 891650 | D11: -47771 | E11: -0.056608827 | F11: 9935999 | G11: 10290782 | H11: -354783 | I11: -0.035706827
A12: Total | B12: 1443033 | C12: 1530203 | D12: -87170 | E12: -0.060407489 | F12: 16990557 | G12: 17563319 | H12: -572762 | I12: -0.033710608
A14: Format codes used
A15: Dec Budget, Dec Actual | B15: $#,##0.0,"K"
A16: Dec Variance, YTD Variance | B16: $#,##0.0,"K";[Red]($#,##0.0,"K")
A17: Dec Var %, YTD Var % | B17: 0.0%;[Red](0.0%)
A18: YTD Budget, YTD Actual | B18: [>=1000000]$#,##0.00,,"M";[>=1000]$#,##0,"K";$#,##0
