Workbook

Sheet Start Here
B2: Lesson 1.5
B3: Relative, Absolute & Mixed References
B4: Beginner · about 45 minutes · Bluestone Health System (fictional)
B6: What you'll learn
B7: • | C7: Predict how relative references change when a formula is copied
B8: • | C8: Lock references with $ (absolute) and use F4 to toggle
B9: • | C9: Build two-way grids with mixed references ($A1 and A$1)
B10: • | C10: Reference other sheets and sum the same cell across sheets (3-D references)
B12: How to use this workbook
B13: 1. Read the guide | C13: The lesson guide (README) explains each skill with examples: https://github.com/lmansf/learn-excel/tree/main/01-foundations/05-cell-references
B14: 2. Practice | C14: Go to the 'Practice' sheet. Type a formula or value into each yellow cell.
B15: 3. Check yourself | C15: The Check column shows ✔ Correct (green) or ✘ Not yet (red). Tasks marked 'See key' are checked by comparing with the answer key.
B16: 4. Bonus | C16: Finished? Try the harder 'Bonus' sheet.
B17: 5. Answers | C17: The 'Answer Key' and 'Bonus Key' sheets are hidden. Right-click any sheet tab → Unhide… → pick one → OK. (Try first!)
B18: Note | C18: The data sheets are plain ranges, not Excel Tables, so the formulas you write use ordinary A1 references with $ signs. (Tables use structured references instead; see Lesson 3.1.)
B19: Note | C19: Staffing Grid, Q4 Summary, and Plan 2026 are layout sheets with yellow grids for you to fill with one formula each.
B20: Note | C20: Keep the Oct, Nov, and Dec tabs together and in that order: 3-D formulas depend on tab positions.
B22: Color legend
B23: Yellow cell | C23: Your answer goes here.
B24: Gray cell | C24: Pre-filled summary formula — it reads the work you did on another sheet.
B25: ✔ Correct | C25: Your answer matches the key.
B26: ✘ Not yet | C26: Not matching yet — check the hint and try again.
B28: Sheets in this workbook
B29: Expenses | C29: Data: 17 rows
B30: Oct | C30: Data: 17 rows
B31: Nov | C31: Data: 17 rows
B32: Dec | C32: Data: 17 rows
B33: 4 West OT | C33: Data: 67 rows
B34: About the data | C34: Bluestone Memorial Hospital's 2025 operating expenses by department and category, the same breakdown for October, November, and December 2025, December 2025 overtime for the hourly staff of Medical-Surgical 4 West, and a 4 West staffing grid.
B35: Disclaimer | C35: All people, places, and numbers are synthetic and fictional. Not clinical guidance.

Sheet Practice
A1: Lesson 1.5 · Practice
A2: Tasks 1, 4, and 8 ask you to predict a formula or reference. Type your answer as text without the leading = (for example AVERAGE(B2:B9)), because Excel would calculate it if you typed the =. The other tasks want a formula in the yellow cell, or work on another sheet that a gray cell checks.
A3: Type a formula or value in each yellow cell. The Check column turns green when your answer matches. Stuck? Read the hint, then the lesson guide. Answers: right-click a sheet tab → Unhide… → 'Answer Key'.
A4: ="Score: "&COUNTIF(E6:E17,"✔*")&" of 12 auto-checked tasks correct"
A5: # | B5: Task | C5: Hint | D5: Your Answer | E5: Check
A6: 1 | B6: On the Expenses sheet, cell J5 contains =SUM(C5:I5), the Emergency Department's total. If you copy J5 and paste it into J14, what formula will J14 contain? Type it without the =, then click J14 to check. | C6: Relative references keep their distance from the formula cell | E6: =IF(IFERROR(D6="",FALSE),"",IF(IFERROR(OR(LOWER(TRIM(D6&""))=LOWER(TRIM('Answer Key'!$C$5&"")),LOWER(TRIM(D6&""))="=sum(c14:i14)"),FALSE),"✔ Correct","✘ Not yet"))
A7: 2 | B7: What share of Bluestone Memorial's 2025 operating expense came from the Intensive Care Unit? Divide the ICU's total (Expenses!J9) by the hospital total (Expenses!J21). Enter it as a percentage. | C7: Type =, click the Expenses tab, click the cell, type /, click the other cell, press Enter | E7: =IF(IFERROR(D7="",FALSE),"",IF(IFERROR(AND(ISNUMBER(D7),OR(ABS(D7-'Answer Key'!$C$6)<=0.00051,ABS(D7-'Answer Key'!$C$6*100)<=0.051000000000000004)),FALSE),"✔ Correct","✘ Not yet"))
A8: 3 | B8: On the Expenses sheet, fill the yellow % of Total column (K5:K20) with ONE formula: type it in K5, lock the reference to the hospital total in J21, then drag the fill handle down to row 20. The gray cell adds up your column. If it shows #DIV/0!, the total reference moved when you copied. | C8: Click J21 in the formula, then press F4 (Mac: ⌘ + T) | D8: {=IF(COUNT(Expenses!K5:K20)=0,"",SUM(Expenses!K5:K20))} | E8: =IF(IFERROR(D8="",FALSE),"",IF(IFERROR(AND(ISNUMBER(D8),OR(ABS(D8-'Answer Key'!$C$7)<=0.00051,ABS(D8-'Answer Key'!$C$7*100)<=0.051000000000000004)),FALSE),"✔ Correct","✘ Not yet"))
A9: 4 | B9: You type =C21 in a cell, leave the cursor in the reference, and press F4 three times (Mac: ⌘ + T three times). Which reference do you end up with? Type it without the =. | C9: Absolute, then row locked, then column locked… | E9: =IF(IFERROR(D9="",FALSE),"",IF(IFERROR(OR(LOWER(TRIM(D9&""))=LOWER(TRIM('Answer Key'!$C$8&"")),LOWER(TRIM(D9&""))="=$c21"),FALSE),"✔ Correct","✘ Not yet"))
A10: 5 | B10: On the 4 West OT sheet, Jessica Aguilar (row 33) worked 9.10 overtime hours in December. On this Practice sheet, write a formula for this employee's overtime pay: OTHours × HourlyRate × the overtime multiplier in B3. Refer to the cells; don't type the numbers. | C10: The sheet name starts with a digit and contains spaces, so it needs single quotes | E10: =IF(IFERROR(D10="",FALSE),"",IF(IFERROR(AND(ISNUMBER(D10),OR(ABS(D10-'Answer Key'!$C$9)<=0.0051)),FALSE),"✔ Correct","✘ Not yet"))
A11: 6 | B11: On the 4 West OT sheet, fill the yellow OTPay column (H6:H72) with one formula: OTHours × HourlyRate × the overtime multiplier in B3. Type it in H6 and copy it down. The gray cell totals your column: what did December's overtime cost? | C11: Lock B3; let the row references move | D11: {=IF(COUNT('4 West OT'!H6:H72)=0,"",SUM('4 West OT'!H6:H72))} | E11: =IF(IFERROR(D11="",FALSE),"",IF(IFERROR(AND(ISNUMBER(D11),OR(ABS(D11-'Answer Key'!$C$10)<=0.0051)),FALSE),"✔ Correct","✘ Not yet"))
A12: 7 | B12: Finance asks what December's overtime would have cost at double time. Change '4 West OT'!B3 to 2, read task 6's gray cell, and type that amount here as a number. Then set B3 back to 1.5. | C12: One edit updates the whole column. That's the point of the rate cell | E12: =IF(IFERROR(D12="",FALSE),"",IF(IFERROR(AND(ISNUMBER(D12),OR(ABS(D12-'Answer Key'!$C$11)<=0.01)),FALSE),"✔ Correct","✘ Not yet"))
A13: 8 | B13: A grid has labels across row 2 and down column A, and cell B3 holds =B$2*$A3. If you copy B3 to D6, what formula will D6 contain? Type it without the =. | C13: A $ freezes only the part right after it | E13: =IF(IFERROR(D13="",FALSE),"",IF(IFERROR(OR(LOWER(TRIM(D13&""))=LOWER(TRIM('Answer Key'!$C$12&"")),LOWER(TRIM(D13&""))="=d$2*$a6"),FALSE),"✔ Correct","✘ Not yet"))
A14: 9 | B14: On the Staffing Grid sheet, fill the yellow grid B6:H12 with ONE formula: nursing hours needed per day = census (column A) × HPPD target (row 5). Type it in B6, copy it across to H6, then down to row 12. The gray cell adds up the whole grid. | C14: Lock the column of the census and the row of the HPPD | D14: {=IF(COUNT('Staffing Grid'!B6:H12)=0,"",SUM('Staffing Grid'!B6:H12))} | E14: =IF(IFERROR(D14="",FALSE),"",IF(IFERROR(AND(ISNUMBER(D14),OR(ABS(D14-'Answer Key'!$C$13)<=0.0001)),FALSE),"✔ Correct","✘ Not yet"))
A15: 10 | B15: Using one 3-D reference, what did Oncology (row 11 on the Oct, Nov, and Dec sheets) spend on Pharmaceuticals (column F) in Q4 2025? | C15: Type =SUM(, click the Oct tab, Shift+click the Dec tab, then click the cell | E15: =IF(IFERROR(D15="",FALSE),"",IF(IFERROR(AND(ISNUMBER(D15),OR(ABS(D15-'Answer Key'!$C$14)<=0.0001)),FALSE),"✔ Correct","✘ Not yet"))
A16: 11 | B16: Fill the yellow grid on the Q4 Summary sheet (C5:I20) with ONE 3-D formula that adds the same cell on the Oct, Nov, and Dec sheets. Type it in C5, copy it across to I5, then down to row 20. The gray cell adds up your grid: what was Bluestone Memorial's Q4 operating expense? | C16: 3-D references copy like ordinary relative references | D16: {=IF(COUNT('Q4 Summary'!C5:I20)=0,"",SUM('Q4 Summary'!C5:I20))} | E16: =IF(IFERROR(D16="",FALSE),"",IF(IFERROR(AND(ISNUMBER(D16),OR(ABS(D16-'Answer Key'!$C$15)<=0.0001)),FALSE),"✔ Correct","✘ Not yet"))
A17: 12 | B17: A colleague drags the Nov tab to the right of the Dec tab. What would =SUM(Oct:Dec!J21) return then? (J21 is each month's hospital total.) Predict it with a formula. If you test it by moving the tab, drag Nov back between Oct and Dec afterwards. | C17: A 3-D range is defined by tab positions, not by month names | E17: =IF(IFERROR(D17="",FALSE),"",IF(IFERROR(AND(ISNUMBER(D17),OR(ABS(D17-'Answer Key'!$C$16)<=0.0001)),FALSE),"✔ Correct","✘ Not yet"))

Sheet Expenses
A1: Bluestone Memorial Hospital · 2025 operating expense by department (actual, $)
A2: Column J (Total) and row 21 (Hospital total) are formulas: click one and read the formula bar. Column K is yours to fill.
A4: Department | B4: Cost Center | C4: Salaries & Wages | D4: Employee Benefits | E4: Medical Supplies | F4: Pharmaceuticals | G4: Purchased Services | H4: Equipment & Maintenance | I4: Other Operating | J4: Total | K4: % of Total
A5: Emergency Department | B5: 6100 | C5: 10290782 | D5: 2857681 | E5: 1381877 | F5: 923543 | G5: 1259187 | H5: 537673 | I5: 312576 | J5: =SUM(C5:I5)
A6: Medical-Surgical 4 West | B6: 6110 | C6: 7354059 | D6: 2139913 | E6: 1064931 | F6: 886875 | G6: 354948 | H6: 210697 | I6: 161038 | J6: =SUM(C6:I6)
A7: Medical-Surgical 5 East | B7: 6111 | C7: 6916992 | D7: 2013494 | E7: 1012628 | F7: 803057 | G7: 304402 | H7: 174314 | I7: 145189 | J7: =SUM(C7:I7)
A8: Cardiac Step-Down | B8: 6120 | C8: 5211816 | D8: 1499676 | E8: 801961 | F8: 590280 | G8: 217058 | H8: 133279 | I8: 103618 | J8: =SUM(C8:I8)
A9: Intensive Care Unit | B9: 6130 | C9: 6780606 | D9: 1939718 | E9: 1112004 | F9: 1000718 | G9: 190029 | H9: 230190 | I9: 90423 | J9: =SUM(C9:I9)
A10: Orthopedics & Spine | B10: 6140 | C10: 4959574 | D10: 1338811 | E10: 729471 | F10: 552401 | G10: 204587 | H10: 121280 | I10: 100463 | J10: =SUM(C10:I10)
A11: Oncology | B11: 6150 | C11: 3798780 | D11: 1027440 | E11: 576822 | F11: 2503860 | G11: 165785 | H11: 109173 | I11: 77443 | J11: =SUM(C11:I11)
A12: Neuroscience & Stroke | B12: 6160 | C12: 3383972 | D12: 976637 | E12: 518673 | F12: 404059 | G12: 149416 | H12: 88731 | I12: 65312 | J12: =SUM(C12:I12)
A13: Labor & Delivery | B13: 6170 | C13: 4461979 | D13: 1138522 | E13: 650550 | F13: 470403 | G13: 191319 | H13: 118175 | I13: 87833 | J13: =SUM(C13:I13)
A14: Pediatrics | B14: 6180 | C14: 2988964 | D14: 808423 | E14: 445725 | F14: 330624 | G14: 139330 | H14: 77940 | I14: 60876 | J14: =SUM(C14:I14)
A15: Behavioral Health | B15: 6190 | C15: 3786381 | D15: 1052992 | E15: 601790 | F15: 479835 | G15: 170283 | H15: 104437 | I15: 77081 | J15: =SUM(C15:I15)
A16: Observation Unit | B16: 6195 | C16: 2471360 | D16: 756063 | E16: 383746 | F16: 306984 | G16: 105890 | H16: 71363 | I16: 52038 | J16: =SUM(C16:I16)
... A20: Pharmacy | B20: 6520 | C20: 3480832 | D20: 926473 | E20: 158394 | F20: 2001898 | G20: 316965 | H20: 195415 | I20: 97631 | J20: =SUM(C20:I20)
A21: Hospital total | C21: =SUM(C5:C20) | D21: =SUM(D5:D20) | E21: =SUM(E5:E20) | F21: =SUM(F5:F20) | G21: =SUM(G5:G20) | H21: =SUM(H5:H20) | I21: =SUM(I5:I20) | J21: =SUM(J5:J20)

Sheet 4 West OT
A1: Medical-Surgical 4 West · overtime for hourly staff · December 2025
A2: OTHours = December's total of paid hours worked beyond each shift's scheduled hours (time clock). Bluestone pays each OT hour at the base HourlyRate × the overtime multiplier in B3 (a simplified, fictional pay rule).
A3: Overtime multiplier | B3: 1.5 | C3: ← time-and-a-half. Every OTPay formula should point here.
A5: EmployeeID | B5: Name | C5: JobTitle | D5: HourlyRate | E5: ShiftsWorked | F5: WorkedHours | G5: OTHours | H5: OTPay
A6: EMP2059 | B6: Nicole Price | C6: Registered Nurse | D6: 38.73 | E6: 15 | F6: 183.12 | G6: 3.32
A7: EMP2060 | B7: Amber Gutierrez | C7: Registered Nurse | D7: 39.37 | E7: 15 | F7: 183.55 | G7: 3.55
A8: EMP2061 | B8: Randy Castro | C8: Registered Nurse | D8: 38.5 | E8: 12 | F8: 146.01 | G8: 2.04
A9: EMP2062 | B9: Lauren Rogers | C9: Registered Nurse | D9: 38.11 | E9: 13 | F9: 160.79 | G9: 4.86
A10: EMP2063 | B10: Sarah Cox | C10: Registered Nurse | D10: 46.74 | E10: 9 | F10: 112.01 | G10: 4.11
A11: EMP2064 | B11: Sarah Moore | C11: Registered Nurse | D11: 38.4 | E11: 2 | F11: 24.32 | G11: 0.32
A12: EMP2066 | B12: Rosa Simmons | C12: Registered Nurse | D12: 44.73 | E12: 12 | F12: 147.25 | G12: 3.35
A13: EMP2067 | B13: Natalie Rose | C13: Registered Nurse | D13: 37.82 | E13: 14 | F13: 172.5 | G13: 4.5
A14: EMP2068 | B14: Abigail Castro | C14: Registered Nurse | D14: 44 | E14: 14 | F14: 175.35 | G14: 7.37
A15: EMP2069 | B15: Jeremy Richards | C15: Registered Nurse | D15: 39.96 | E15: 15 | F15: 186.96 | G15: 7.11
A16: EMP2070 | B16: Melissa Simpson | C16: Registered Nurse | D16: 54.06 | E16: 12 | F16: 147.31 | G16: 3.31
A17: EMP2071 | B17: Amina Gordon | C17: Registered Nurse | D17: 37.87 | E17: 6 | F17: 74.07 | G17: 2.07
... A72: EMP2130 | B72: Alexander Arnold | C72: Respiratory Therapist | D72: 39.47 | E72: 3 | F72: 37.92 | G72: 1.92

Sheet Staffing Grid
A1: Medical-Surgical 4 West · nursing care hours needed per day
A2: Hours needed = midnight census (column A) × HPPD target (row 5). HPPD = nursing hours per patient day.
A3: Fill the yellow grid B6:H12 with ONE formula: type it in B6, copy it across to H6, then down to row 12.
A5: Census ↓ HPPD → | B5: 7 | C5: 7.5 | D5: 8 | E5: 8.5 | F5: 9 | G5: 9.5 | H5: 10
A6: 26
A7: 28
A8: 30
A9: 32
A10: 34
A11: 36
A12: 38

Sheet Q4 Summary
A1: Bluestone Memorial Hospital · Q4 2025 operating expense, October–December ($)
A2: Same layout as the Oct, Nov, and Dec sheets. Fill the yellow grid with ONE 3-D formula that adds the same cell on all three monthly sheets, then copy it across and down.
A4: Department | B4: Cost Center | C4: Salaries & Wages | D4: Employee Benefits | E4: Medical Supplies | F4: Pharmaceuticals | G4: Purchased Services | H4: Equipment & Maintenance | I4: Other Operating | J4: Total
A5: Emergency Department | B5: 6100 | J5: =SUM(C5:I5)
A6: Medical-Surgical 4 West | B6: 6110 | J6: =SUM(C6:I6)
A7: Medical-Surgical 5 East | B7: 6111 | J7: =SUM(C7:I7)
A8: Cardiac Step-Down | B8: 6120 | J8: =SUM(C8:I8)
A9: Intensive Care Unit | B9: 6130 | J9: =SUM(C9:I9)
A10: Orthopedics & Spine | B10: 6140 | J10: =SUM(C10:I10)
A11: Oncology | B11: 6150 | J11: =SUM(C11:I11)
A12: Neuroscience & Stroke | B12: 6160 | J12: =SUM(C12:I12)
A13: Labor & Delivery | B13: 6170 | J13: =SUM(C13:I13)
A14: Pediatrics | B14: 6180 | J14: =SUM(C14:I14)
A15: Behavioral Health | B15: 6190 | J15: =SUM(C15:I15)
A16: Observation Unit | B16: 6195 | J16: =SUM(C16:I16)
... A20: Pharmacy | B20: 6520 | J20: =SUM(C20:I20)
A21: Hospital total | C21: =SUM(C5:C20) | D21: =SUM(D5:D20) | E21: =SUM(E5:E20) | F21: =SUM(F5:F20) | G21: =SUM(G5:G20) | H21: =SUM(H5:H20) | I21: =SUM(I5:I20) | J21: =SUM(J5:J20)

Sheet Oct
A1: Bluestone Memorial Hospital · operating expense actuals · October 2025 ($)
A2: Oct, Nov, and Dec share one layout: departments in rows 5–20, categories in columns C–I, totals in column J and row 21.
A4: Department | B4: Cost Center | C4: Salaries & Wages | D4: Employee Benefits | E4: Medical Supplies | F4: Pharmaceuticals | G4: Purchased Services | H4: Equipment & Maintenance | I4: Other Operating | J4: Total
A5: Emergency Department | B5: 6100 | C5: 859807 | D5: 232299 | E5: 97503 | F5: 85627 | G5: 89467 | H5: 46210 | I5: 24521 | J5: =SUM(C5:I5)
A6: Medical-Surgical 4 West | B6: 6110 | C6: 609878 | D6: 181713 | E6: 76462 | F6: 75644 | G6: 29795 | H6: 20004 | I6: 15196 | J6: =SUM(C6:I6)
A7: Medical-Surgical 5 East | B7: 6111 | C7: 599680 | D7: 165104 | E7: 86990 | F7: 62880 | G7: 24964 | H7: 15222 | I7: 11542 | J7: =SUM(C7:I7)
A8: Cardiac Step-Down | B8: 6120 | C8: 451984 | D8: 125725 | E8: 66479 | F8: 54810 | G8: 18551 | H8: 11209 | I8: 9287 | J8: =SUM(C8:I8)
A9: Intensive Care Unit | B9: 6130 | C9: 566232 | D9: 166473 | E9: 86967 | F9: 82101 | G9: 14652 | H9: 19993 | I9: 7193 | J9: =SUM(C9:I9)
A10: Orthopedics & Spine | B10: 6140 | C10: 411167 | D10: 111442 | E10: 62684 | F10: 42484 | G10: 16135 | H10: 10841 | I10: 8739 | J10: =SUM(C10:I10)
A11: Oncology | B11: 6150 | C11: 326993 | D11: 85593 | E11: 56899 | F11: 228126 | G11: 15885 | H11: 9307 | I11: 6869 | J11: =SUM(C11:I11)
A12: Neuroscience & Stroke | B12: 6160 | C12: 284946 | D12: 82257 | E12: 45941 | F12: 32573 | G12: 12372 | H12: 7004 | I12: 5049 | J12: =SUM(C12:I12)
A13: Labor & Delivery | B13: 6170 | C13: 381189 | D13: 102522 | E13: 61984 | F13: 41046 | G13: 16013 | H13: 9826 | I13: 6632 | J13: =SUM(C13:I13)
A14: Pediatrics | B14: 6180 | C14: 244533 | D14: 67115 | E14: 41432 | F14: 31032 | G14: 10211 | H14: 6068 | I14: 5398 | J14: =SUM(C14:I14)
A15: Behavioral Health | B15: 6190 | C15: 304466 | D15: 86793 | E15: 48832 | F15: 35985 | G15: 11946 | H15: 9142 | I15: 6890 | J15: =SUM(C15:I15)
A16: Observation Unit | B16: 6195 | C16: 204669 | D16: 63782 | E16: 29806 | F16: 27659 | G16: 8867 | H16: 6291 | I16: 4455 | J16: =SUM(C16:I16)
... A20: Pharmacy | B20: 6520 | C20: 296381 | D20: 77068 | E20: 12982 | F20: 193756 | G20: 27805 | H20: 17576 | I20: 8322 | J20: =SUM(C20:I20)
A21: Hospital total | C21: =SUM(C5:C20) | D21: =SUM(D5:D20) | E21: =SUM(E5:E20) | F21: =SUM(F5:F20) | G21: =SUM(G5:G20) | H21: =SUM(H5:H20) | I21: =SUM(I5:I20) | J21: =SUM(J5:J20)

Sheet Nov
A1: Bluestone Memorial Hospital · operating expense actuals · November 2025 ($)
A2: Oct, Nov, and Dec share one layout: departments in rows 5–20, categories in columns C–I, totals in column J and row 21.
A4: Department | B4: Cost Center | C4: Salaries & Wages | D4: Employee Benefits | E4: Medical Supplies | F4: Pharmaceuticals | G4: Purchased Services | H4: Equipment & Maintenance | I4: Other Operating | J4: Total
A5: Emergency Department | B5: 6100 | C5: 866792 | D5: 230591 | E5: 119846 | F5: 62990 | G5: 111637 | H5: 39430 | I5: 28240 | J5: =SUM(C5:I5)
A6: Medical-Surgical 4 West | B6: 6110 | C6: 611966 | D6: 167541 | E6: 80707 | F6: 65253 | G6: 31424 | H6: 16051 | I6: 14017 | J6: =SUM(C6:I6)
A7: Medical-Surgical 5 East | B7: 6111 | C7: 580452 | D7: 163495 | E7: 75365 | F7: 65831 | G7: 22546 | H7: 12826 | I7: 9450 | J7: =SUM(C7:I7)
A8: Cardiac Step-Down | B8: 6120 | C8: 409192 | D8: 126351 | E8: 69222 | F8: 51406 | G8: 17785 | H8: 13167 | I8: 8512 | J8: =SUM(C8:I8)
A9: Intensive Care Unit | B9: 6130 | C9: 531571 | D9: 156313 | E9: 89976 | F9: 71836 | G9: 15722 | H9: 18722 | I9: 7502 | J9: =SUM(C9:I9)
A10: Orthopedics & Spine | B10: 6140 | C10: 412763 | D10: 108793 | E10: 62524 | F10: 53670 | G10: 16098 | H10: 9949 | I10: 7316 | J10: =SUM(C10:I10)
A11: Oncology | B11: 6150 | C11: 309964 | D11: 81815 | E11: 48373 | F11: 207259 | G11: 13532 | H11: 8684 | I11: 6358 | J11: =SUM(C11:I11)
A12: Neuroscience & Stroke | B12: 6160 | C12: 276179 | D12: 81456 | E12: 37776 | F12: 36286 | G12: 12550 | H12: 6602 | I12: 5092 | J12: =SUM(C12:I12)
A13: Labor & Delivery | B13: 6170 | C13: 364127 | D13: 88520 | E13: 47734 | F13: 39884 | G13: 14889 | H13: 9528 | I13: 7787 | J13: =SUM(C13:I13)
A14: Pediatrics | B14: 6180 | C14: 245142 | D14: 65619 | E14: 37087 | F14: 31123 | G14: 10997 | H14: 5467 | I14: 4307 | J14: =SUM(C14:I14)
A15: Behavioral Health | B15: 6190 | C15: 303299 | D15: 88274 | E15: 48224 | F15: 35773 | G15: 14693 | H15: 8832 | I15: 6752 | J15: =SUM(C15:I15)
A16: Observation Unit | B16: 6195 | C16: 198151 | D16: 61786 | E16: 30532 | F16: 27066 | G16: 7698 | H16: 5472 | I16: 4346 | J16: =SUM(C16:I16)
... A20: Pharmacy | B20: 6520 | C20: 292504 | D20: 74207 | E20: 12834 | F20: 182806 | G20: 26774 | H20: 16801 | I20: 8002 | J20: =SUM(C20:I20)
A21: Hospital total | C21: =SUM(C5:C20) | D21: =SUM(D5:D20) | E21: =SUM(E5:E20) | F21: =SUM(F5:F20) | G21: =SUM(G5:G20) | H21: =SUM(H5:H20) | I21: =SUM(I5:I20) | J21: =SUM(J5:J20)

Sheet Dec
A1: Bluestone Memorial Hospital · operating expense actuals · December 2025 ($)
A2: Oct, Nov, and Dec share one layout: departments in rows 5–20, categories in columns C–I, totals in column J and row 21.
A4: Department | B4: Cost Center | C4: Salaries & Wages | D4: Employee Benefits | E4: Medical Supplies | F4: Pharmaceuticals | G4: Purchased Services | H4: Equipment & Maintenance | I4: Other Operating | J4: Total
A5: Emergency Department | B5: 6100 | C5: 891650 | D5: 261689 | E5: 114612 | F5: 71566 | G5: 117116 | H5: 48423 | I5: 25147 | J5: =SUM(C5:I5)
A6: Medical-Surgical 4 West | B6: 6110 | C6: 652699 | D6: 188262 | E6: 102937 | F6: 86540 | G6: 30578 | H6: 18446 | I6: 14058 | J6: =SUM(C6:I6)
A7: Medical-Surgical 5 East | B7: 6111 | C7: 597989 | D7: 174378 | E7: 93904 | F7: 77870 | G7: 26577 | H7: 17353 | I7: 13122 | J7: =SUM(C7:I7)
A8: Cardiac Step-Down | B8: 6120 | C8: 447282 | D8: 134567 | E8: 70011 | F8: 56547 | G8: 17890 | H8: 9785 | I8: 9895 | J8: =SUM(C8:I8)
A9: Intensive Care Unit | B9: 6130 | C9: 600520 | D9: 172549 | E9: 102650 | F9: 90727 | G9: 16179 | H9: 17442 | I9: 7940 | J9: =SUM(C9:I9)
A10: Orthopedics & Spine | B10: 6140 | C10: 433334 | D10: 113429 | E10: 67091 | F10: 41882 | G10: 16782 | H10: 9712 | I10: 9540 | J10: =SUM(C10:I10)
A11: Oncology | B11: 6150 | C11: 316054 | D11: 85668 | E11: 46479 | F11: 219248 | G11: 14217 | H11: 7743 | I11: 6164 | J11: =SUM(C11:I11)
A12: Neuroscience & Stroke | B12: 6160 | C12: 316944 | D12: 86848 | E12: 43078 | F12: 34408 | G12: 13196 | H12: 8002 | I12: 5774 | J12: =SUM(C12:I12)
A13: Labor & Delivery | B13: 6170 | C13: 400396 | D13: 100259 | E13: 57801 | F13: 38022 | G13: 17602 | H13: 9567 | I13: 7318 | J13: =SUM(C13:I13)
A14: Pediatrics | B14: 6180 | C14: 259815 | D14: 74313 | E14: 36048 | F14: 28796 | G14: 9758 | H14: 6651 | I14: 4793 | J14: =SUM(C14:I14)
A15: Behavioral Health | B15: 6190 | C15: 325457 | D15: 94060 | E15: 53345 | F15: 40937 | G15: 14271 | H15: 9139 | I15: 6772 | J15: =SUM(C15:I15)
A16: Observation Unit | B16: 6195 | C16: 218120 | D16: 65739 | E16: 34864 | F16: 25365 | G16: 9015 | H16: 6027 | I16: 4247 | J16: =SUM(C16:I16)
... A20: Pharmacy | B20: 6520 | C20: 302308 | D20: 81623 | E20: 11274 | F20: 147308 | G20: 24590 | H20: 15232 | I20: 8254 | J20: =SUM(C20:I20)
A21: Hospital total | C21: =SUM(C5:C20) | D21: =SUM(D5:D20) | E21: =SUM(E5:E20) | F21: =SUM(F5:F20) | G21: =SUM(G5:G20) | H21: =SUM(H5:H20) | I21: =SUM(I5:I20) | J21: =SUM(J5:J20)

Sheet Bonus
A1: Lesson 1.5 · Bonus: Build the 2026 expense plan
A2: Finance needs a first-draft 2026 operating expense plan for Bluestone Memorial. The rule: each 2026 cell = the 2025 actual for the same department and category (Expenses sheet) × (1 + that category's price inflation in row 3 of the Plan 2026 sheet) × (1 + that department's volume growth in column B). The Plan 2026 sheet uses the same rows and columns as the Expenses sheet. Column J and row 21 of Plan 2026 already total whatever you put in the grid.
A3: Type a formula or value in each yellow cell. The Check column turns green when your answer matches. Stuck? Read the hint, then the lesson guide. Answers: right-click a sheet tab → Unhide… → 'Bonus Key'.
A4: ="Score: "&COUNTIF(E6:E10,"✔*")&" of 5 auto-checked tasks correct"
A5: # | B5: Task | C5: Hint | D5: Your Answer | E5: Check
A6: B1 | B6: Fill the yellow grid on the Plan 2026 sheet (C5:I20) with ONE formula typed in C5 and copied across and down. The gray cell adds up your grid: what is the 2026 plan total? (Don't round.) | C6: The 2025 actual moves both ways, the inflation row is locked, and the growth column is locked | D6: {=IF(COUNT('Plan 2026'!C5:I20)=0,"",SUM('Plan 2026'!C5:I20))} | E6: =IF(IFERROR(D6="",FALSE),"",IF(IFERROR(AND(ISNUMBER(D6),OR(ABS(D6-'Bonus Key'!$C$5)<=0.0051)),FALSE),"✔ Correct","✘ Not yet"))
A7: B2 | B7: What is the 2026 plan for Laboratory · Medical Supplies (Plan 2026, row 18, column E)? Reference the cell in your grid. | C7: Check it by hand: 2025 amount × (1 + inflation) × (1 + growth) | E7: =IF(IFERROR(D7="",FALSE),"",IF(IFERROR(AND(ISNUMBER(D7),OR(ABS(D7-'Bonus Key'!$C$6)<=0.5)),FALSE),"✔ Correct","✘ Not yet"))
A8: B3 | B8: By what percentage would Bluestone Memorial's total operating expense grow from 2025 to 2026 under this plan? Enter it as a percentage. | C8: New ÷ old − 1 | E8: =IF(IFERROR(D8="",FALSE),"",IF(IFERROR(AND(ISNUMBER(D8),OR(ABS(D8-'Bonus Key'!$C$7)<=0.00051,ABS(D8-'Bonus Key'!$C$7*100)<=0.051000000000000004)),FALSE),"✔ Correct","✘ Not yet"))
A9: B4 | B9: Which department's total expense is planned to grow by the largest percentage? Type the department name exactly as it appears in column A. | C9: Add a helper column that divides each department's 2026 total by its 2025 total | E9: =IF(IFERROR(D9="",FALSE),"",IF(IFERROR(OR(LOWER(TRIM(D9&""))=LOWER(TRIM('Bonus Key'!$C$8&""))),FALSE),"✔ Correct","✘ Not yet"))
A10: B5 | B10: Pharmaceutical prices are the shakiest assumption. If pharmaceutical inflation were 9.0% instead of 7.5%, how many dollars higher would the 2026 plan total be? Change the one input cell, compare the totals, then put it back. Round to the nearest dollar. | C10: Because of the $ signs, one edit flows to all 16 Pharmaceuticals cells | E10: =IF(IFERROR(D10="",FALSE),"",IF(IFERROR(AND(ISNUMBER(D10),OR(ABS(D10-'Bonus Key'!$C$9)<=1)),FALSE),"✔ Correct","✘ Not yet"))

Sheet Plan 2026
A1: Bluestone Memorial Hospital · 2026 operating expense plan ($)
A2: 2026 = 2025 actual from the Expenses sheet (same cell) × (1 + price inflation in row 3) × (1 + volume growth in column B). Blue cells are planning assumptions.
A3: Price inflation → | C3: 0.035 | D3: 0.06 | E3: 0.04 | F3: 0.075 | G3: 0.03 | H3: 0.025 | I3: 0.02
A4: Department | B4: Volume growth | C4: Salaries & Wages | D4: Employee Benefits | E4: Medical Supplies | F4: Pharmaceuticals | G4: Purchased Services | H4: Equipment & Maintenance | I4: Other Operating | J4: Total 2026
A5: Emergency Department | B5: 0.03 | J5: =SUM(C5:I5)
A6: Medical-Surgical 4 West | B6: 0.01 | J6: =SUM(C6:I6)
A7: Medical-Surgical 5 East | B7: 0.005 | J7: =SUM(C7:I7)
A8: Cardiac Step-Down | B8: 0.02 | J8: =SUM(C8:I8)
A9: Intensive Care Unit | B9: 0.025 | J9: =SUM(C9:I9)
A10: Orthopedics & Spine | B10: 0.035 | J10: =SUM(C10:I10)
A11: Oncology | B11: 0.045 | J11: =SUM(C11:I11)
A12: Neuroscience & Stroke | B12: 0.035 | J12: =SUM(C12:I12)
A13: Labor & Delivery | B13: 0.015 | J13: =SUM(C13:I13)
A14: Pediatrics | B14: -0.02 | J14: =SUM(C14:I14)
A15: Behavioral Health | B15: 0.03 | J15: =SUM(C15:I15)
A16: Observation Unit | B16: 0.05 | J16: =SUM(C16:I16)
... A20: Pharmacy | B20: 0.03 | J20: =SUM(C20:I20)
A21: Hospital total 2026 | C21: =SUM(C5:C20) | D21: =SUM(D5:D20) | E21: =SUM(E5:E20) | F21: =SUM(F5:F20) | G21: =SUM(G5:G20) | H21: =SUM(H5:H20) | I21: =SUM(I5:I20) | J21: =SUM(J5:J20)

Sheet Answer Key
A1: 🔑 Answer Key — Lesson 1.5
A2: Spoiler alert — try every task before reading this sheet. Column C is the value the Check column compares against. Column D is a sample solution; column E is that same formula, live, proving it works.
A4: # | B4: Task | C4: Answer | D4: Sample solution | E4: Live result | F4: Explanation
A5: 1 | B5: On the Expenses sheet, cell J5 contains =SUM(C5:I5), the Emergency Department's total. If you copy J5 and paste it into J14, what formula will J14 contain? Type it without the =, then click J14 to check. | C5: SUM(C14:I14) | D5: Count the move: from row 5 to row 14 is 9 rows down and 0 columns across. Add 9 to every row number in the formula and leave the column letters alone. | E5: — | F5: Excel stores =SUM(C5:I5) in J5 as "the seven cells to my left, on my row." Pasted into J14, the same instruction points at C14:I14. That's why one total formula works for every department.
A6: 2 | B6: What share of Bluestone Memorial's 2025 operating expense came from the Intensive Care Unit? Divide the ICU's total (Expenses!J9) by the hospital total (Expenses!J21). Enter it as a percentage. | C6: 0.074697207 | D6: =Expenses!J9/Expenses!J21 | E6: {=Expenses!J9/Expenses!J21} | F6: A reference to another sheet is the sheet name, an exclamation mark, then the cell. If you build it by clicking, Excel writes the Expenses! part for you. Press Enter while you're still on the Expenses sheet, and Excel takes you back to Practice.
A7: 3 | B7: On the Expenses sheet, fill the yellow % of Total column (K5:K20) with ONE formula: type it in K5, lock the reference to the hospital total in J21, then drag the fill handle down to row 20. The gray cell adds up your column. If it shows #DIV/0!, the total reference moved when you copied. | C7: 1 | D7: =J5/$J$21 | E7: {=SUM(Expenses!J5:J20)/Expenses!J21} | F7: Without the $ signs, K6 would hold =J6/J22. Row 22 is empty, so the result is #DIV/0!. $J$21 stays put wherever you copy it, while J5 moves to each department's row. =J5/J$21 also works here, because you only copy down. Every % of total column adds up to 100%, so the gray cell doubles as a sanity check.
A8: 4 | B8: You type =C21 in a cell, leave the cursor in the reference, and press F4 three times (Mac: ⌘ + T three times). Which reference do you end up with? Type it without the =. | C8: $C21 | D8: F4 cycles C21 → $C$21 → C$21 → $C21 → back to C21. The third press gives **$C21**. | E8: — | F8: $C21 locks the column (C) but lets the row change. Try it: type the formula, press F4 three times, and watch the formula bar. Press Esc afterwards so you don't leave the test formula in the sheet.
A9: 5 | B9: On the 4 West OT sheet, Jessica Aguilar (row 33) worked 9.10 overtime hours in December. On this Practice sheet, write a formula for this employee's overtime pay: OTHours × HourlyRate × the overtime multiplier in B3. Refer to the cells; don't type the numbers. | C9: 559.65 | D9: ='4 West OT'!G33*'4 West OT'!D33*'4 West OT'!B3 | E9: {='4 West OT'!G33*'4 West OT'!D33*'4 West OT'!B3} | F9: Sheet names that contain spaces or start with a digit must be wrapped in single quotes: '4 West OT'!B3. When you click the cells instead of typing, Excel adds the quotes for you. No $ signs are needed here, because this formula is never copied.
A10: 6 | B10: On the 4 West OT sheet, fill the yellow OTPay column (H6:H72) with one formula: OTHours × HourlyRate × the overtime multiplier in B3. Type it in H6 and copy it down. The gray cell totals your column: what did December's overtime cost? | C10: 16029.432 | D10: =G6*D6*$B$3 | E10: {=SUMPRODUCT('4 West OT'!G6:G72,'4 West OT'!D6:D72)*'4 West OT'!B3} | F10: G6 and D6 are relative, so each row uses its own employee's hours and rate. $B$3 is absolute, so all 67 rows share the one multiplier cell. If you had typed *1.5 into every formula, a policy change would mean editing 67 formulas.
A11: 7 | B11: Finance asks what December's overtime would have cost at double time. Change '4 West OT'!B3 to 2, read task 6's gray cell, and type that amount here as a number. Then set B3 back to 1.5. | C11: 21372.577 | D11: 1. Click **'4 West OT'!B3**, type `2`, and press **Enter**. 2. Read the gray cell in task 6 and type that amount into this task's yellow cell. 3. Change B3 back to `1.5` so tasks 5 and 6 show ✔ again. | E11: {=SUMPRODUCT('4 West OT'!G6:G72,'4 West OT'!D6:D72)*2} | F11: Because every OTPay formula points at B3, one edit recalculates all 67 rows and the total. This is the payoff of the rate-in-one-cell pattern: assumptions live in one labeled cell, so what-if questions take seconds.
A12: 8 | B12: A grid has labels across row 2 and down column A, and cell B3 holds =B$2*$A3. If you copy B3 to D6, what formula will D6 contain? Type it without the =. | C12: D$2*$A6 | D12: The move is 2 columns right (B to D) and 3 rows down (row 3 to row 6). In B$2 the row is locked, so only the column moves and it becomes D$2. In $A3 the column is locked, so only the row moves and it becomes $A6. The answer is **=D$2*$A6**. | E12: — | F12: B$2 always reads row 2 (the labels across the top) in the current column. $A3 always reads column A (the labels down the side) in the current row. Together they make every cell multiply its own column label by its own row label, which is exactly what a two-way grid needs. You'll build one in the next task.
A13: 9 | B13: On the Staffing Grid sheet, fill the yellow grid B6:H12 with ONE formula: nursing hours needed per day = census (column A) × HPPD target (row 5). Type it in B6, copy it across to H6, then down to row 12. The gray cell adds up the whole grid. | C13: 13328 | D13: =$A6*B$5 | E13: {=SUM('Staffing Grid'!A6:A12)*SUM('Staffing Grid'!B5:H5)} | F13: $A6 keeps every formula looking at column A, and B$5 keeps every formula looking at row 5. With =$A$6*$B$5, every cell would repeat 182, the B6 result. With no $ at all, C6 would compute =B6*C5, multiplying the previous result by the HPPD instead of using the census. Cross-check: the sum of a multiplication grid equals (sum of the census values) × (sum of the HPPD targets), which is how the key's live formula works.
A14: 10 | B14: Using one 3-D reference, what did Oncology (row 11 on the Oct, Nov, and Dec sheets) spend on Pharmaceuticals (column F) in Q4 2025? | C14: 654633 | D14: =SUM(Oct:Dec!F11) | E14: =SUM(Oct:Dec!F11) | F14: Oct:Dec! means every sheet from the Oct tab through the Dec tab, so the formula adds F11 on all three. It's the same as =Oct!F11+Nov!F11+Dec!F11, but it stays short no matter how many monthly sheets sit between the two end tabs.
A15: 11 | B15: Fill the yellow grid on the Q4 Summary sheet (C5:I20) with ONE 3-D formula that adds the same cell on the Oct, Nov, and Dec sheets. Type it in C5, copy it across to I5, then down to row 20. The gray cell adds up your grid: what was Bluestone Memorial's Q4 operating expense? | C15: 38299957 | D15: =SUM(Oct:Dec!C5) | E15: =SUM(Oct:Dec!C5:I20) | F15: The cell part of Oct:Dec!C5 is relative, so copying moves it exactly like a normal reference: I20 ends up as =SUM(Oct:Dec!I20). This only works because the three monthly sheets share one layout. A 3-D reference adds cells by position, not by department name. Q4 Summary sits to the left of Oct, outside the Oct:Dec range, so it never adds itself.
A16: 12 | B16: A colleague drags the Nov tab to the right of the Dec tab. What would =SUM(Oct:Dec!J21) return then? (J21 is each month's hospital total.) Predict it with a formula. If you test it by moving the tab, drag Nov back between Oct and Dec afterwards. | C16: 25941245 | D16: =Oct!J21+Dec!J21 | E16: {=Oct!J21+Dec!J21} | F16: Oct:Dec! means "Oct, Dec, and whatever tabs sit between them right now." Once Nov is dragged past Dec, it's outside the sandwich, so the total silently drops November. A sheet dragged in between the end tabs gets added just as silently. Keep 3-D sheets in order, and consider empty "bookend" sheets (for example First and Last) that mark the range.

Sheet Bonus Key
A1: 🔑 Bonus Key — Lesson 1.5
A2: Spoiler alert — try every task before reading this sheet. Column C is the value the Check column compares against. Column D is a sample solution; column E is that same formula, live, proving it works.
A4: # | B4: Task | C4: Answer | D4: Sample solution | E4: Live result | F4: Explanation
A5: B1 | B5: Fill the yellow grid on the Plan 2026 sheet (C5:I20) with ONE formula typed in C5 and copied across and down. The gray cell adds up your grid: what is the 2026 plan total? (Don't round.) | C5: 1.6221946e+08 | D5: =Expenses!C5*(1+C$3)*(1+$B5) | E5: {=SUMPRODUCT(Expenses!C5:I20*(1+'Plan 2026'!C3:I3)*(1+'Plan 2026'!B5:B20))} | F5: Expenses!C5 is fully relative, because each plan cell needs the matching 2025 cell. C$3 locks the row, so every department reads the inflation in row 3 of its own category column. $B5 locks the column, so every category reads the growth in column B of its own department row. One formula, three reference types, 112 correct cells.
A6: B2 | B6: What is the 2026 plan for Laboratory · Medical Supplies (Plan 2026, row 18, column E)? Reference the cell in your grid. | C6: 3424829.9 | D6: ='Plan 2026'!E18 | E6: {=Expenses!E18*(1+'Plan 2026'!E3)*(1+'Plan 2026'!B18)} | F6: Spot-checking a cell far from where you typed the formula proves the copy worked. E18 should hold =Expenses!E18*(1+E$3)*(1+$B18): the inflation is still read from row 3 and the growth from column B.
A7: B3 | B7: By what percentage would Bluestone Memorial's total operating expense grow from 2025 to 2026 under this plan? Enter it as a percentage. | C7: 0.068201119 | D7: ='Plan 2026'!J21/Expenses!J21-1 | E7: {=SUMPRODUCT(Expenses!C5:I20*(1+'Plan 2026'!C3:I3)*(1+'Plan 2026'!B5:B20))/Expenses!J21-1} | F7: 'Plan 2026'!J21 is the 2026 grand total and Expenses!J21 is the 2025 grand total. New ÷ old − 1 turns the two totals into a growth rate.
A8: B4 | B8: Which department's total expense is planned to grow by the largest percentage? Type the department name exactly as it appears in column A. | C8: Oncology | D8: 1. In 'Plan 2026'!K5, type `=J5/Expenses!J5-1` and copy it down to K20. Both references are relative, so each row compares its own department. 2. Format K5:K20 as a percentage and find the largest value (`=MAX(K5:K20)` helps). 3. Read the department name in column A of that row. | E8: — | F8: Oncology grows 9.7%, ahead of Observation Unit at 9.5%, even though Observation Unit has the highest volume growth (5.0%). Oncology's spending is heavy in Pharmaceuticals, the category with the steepest inflation (7.5%), so its mix pushes the total up faster.
A9: B5 | B9: Pharmaceutical prices are the shakiest assumption. If pharmaceutical inflation were 9.0% instead of 7.5%, how many dollars higher would the 2026 plan total be? Change the one input cell, compare the totals, then put it back. Round to the nearest dollar. | C9: 176282 | D9: 1. Note the plan total in 'Plan 2026'!J21 (or the gray cell in B1). 2. Change 'Plan 2026'!F3 from 7.5% to 9.0%. 3. Subtract the old total from the new one and round to the nearest dollar. 4. Set F3 back to 7.5%. | E9: {=ROUND(SUMPRODUCT(Expenses!F5:F20*(1+'Plan 2026'!B5:B20))*(0.09-'Plan 2026'!F3),0)} | F9: Only the Pharmaceuticals column reads that input, so only those 16 cells change. Each one rises by its 2025 amount × (1 + growth) × 1.5 percentage points. Testing the shakiest assumption like this is called a sensitivity check, and it only takes seconds because the assumption lives in one cell.
